CHANGELOG.rst
LICENSE
MANIFEST.in
README.rst
setup.cfg
setup.py
mal_analytics/__init__.py
mal_analytics/db_manager.py
mal_analytics/exceptions.py
mal_analytics/profiler_parser.py
mal_analytics/trace_reader.py
mal_analytics.egg-info/PKG-INFO
mal_analytics.egg-info/SOURCES.txt
mal_analytics.egg-info/dependency_links.txt
mal_analytics.egg-info/requires.txt
mal_analytics.egg-info/top_level.txt
mal_analytics/data/add_constraints.sql
mal_analytics/data/drop_constraints.sql
mal_analytics/data/tables.sql