Metadata-Version: 2.1
Name: mal-analytics
Version: 0.1.0
Summary: UNKNOWN
Home-page: https://github.com/MonetDBSolutions/mal_analytics
Author: Panagiotis Koutsourakis
Author-email: panagiotis.koutsourakis@monetdbsolutions.com
License: UNKNOWN
Platform: UNKNOWN
Classifier: License :: OSI Approved :: Mozilla Public License 2.0 (MPL 2.0)
Classifier: Programming Language :: Python :: 3.5
Classifier: Programming Language :: Python :: 3.6
Classifier: Programming Language :: Python :: 3.7
Classifier: Topic :: Database
Classifier: Topic :: Database :: Database Engines/Servers
Classifier: Intended Audience :: Developers
Classifier: Development Status :: 3 - Alpha
